memory/ram.v
module ram (
  output reg [7:0] data_out,
  input [7:0] data_in,
  input [9:0] addr,
  input wr,          // Write enable
  input cs           // Chip select
);
  reg [7:0] mem [0:1023];

  // Write operation
  always @(*) begin
    if (cs && wr)
      mem[addr] = data_in;
  end

  // Read operation (combinational)
  always @(*) begin
    if (cs && !wr)
      data_out = mem[addr];
    else
      data_out = 8'bz; // High impedance if not reading
  end
endmodule

memory/ram_tb.v
module ram_test;
  reg [9:0] address;
  wire [7:0] data_out;
  reg [7:0] data_in;
  reg write, select;
  integer k, myseed;

  // Instantiate the RAM module
  ram dut (
    .data_out(data_out),
    .data_in(data_in),
    .addr(address),
    .wr(write),
    .cs(select)
  );
  
  initial begin
    $dumpfile("dut.vcd");
    $dumpvars;
  end

  initial begin
    myseed = 35;

    // Writing data into RAM
    for (k = 0; k <= 1023; k = k + 1) begin
      address = k;
      data_in = (k + k) % 256;
      write = 1;
      select = 1;
      #2;
      write = 0;
      select = 0;
      #1;
    end

    // Reading random data from RAM
    $display("\n--- Reading Random Memory Locations ---");
    repeat (20) begin
      address = $random(myseed) % 1024;
      write = 0;
      select = 1;
      #2;  // Allow some time for data_out to settle
      $display("Address: %5d  Data read: %4d", address, data_out);
      select = 0;
      #1;
    end

    $finish;
  end
endmodule

memory/dut.vcd
$date
	Wed Jul 09 13:45:41 2025
$end
$version
	Icarus Verilog
$end
$timescale
	1s
$end
$scope module ram_test $end
$var wire 8 ! data_out [7:0] $end
$var reg 10 " address [9:0] $end
$var reg 8 # data_in [7:0] $end
$var reg 1 $ select $end
$var reg 1 % write $end
$var integer 32 & k [31:0] $end
$var integer 32 ' myseed [31:0] $end
$scope module dut $end
$var wire 10 ( addr [9:0] $end
$var wire 1 $ cs $end
$var wire 8 ) data_in [7:0] $end
$var wire 1 % wr $end
$var reg 8 * data_out [7:0] $end
$upscope $end
$upscope $end
$enddefinitions $end
$comment Show the parameter values. $end
$dumpall
$end
#0
$dumpvars
bz *
b0 )
b0 (
b100011 '
b0 &
1%
1$
b0 #
b0 "
bz !
$end
#2
0$
0%
#3
1$
1%
b10 #
b10 )
b1 "
b1 (
b1 &
#5
0$
0%
#6
1$
1%
b100 #
b100 )
b10 "
b10 (
b10 &
#8
0$
0%
#9
1$
1%
b110 #
b110 )
b11 "
b11 (
b11 &
#11
0$
0%
#12
1$
1%
b1000 #
b1000 )
b100 "
b100 (
b100 &
#14
0$
0%
#15
1$
1%
b1010 #
b1010 )
b101 "
b101 (
b101 &
#17
0$
0%
#18
1$
1%
b1100 #
b1100 )
b110 "
b110 (
b110 &
#20
0$
0%
#21
1$
1%
b1110 #
b1110 )
b111 "
b111 (
b111 &
#23
0$
0%
#24
1$
1%
b10000 #
b10000 )
b1000 "
b1000 (
b1000 &
#26
0$
0%
#27
1$
1%
b10010 #
b10010 )
b1001 "
b1001 (
b1001 &
#29
0$
0%
#30
1$
1%
b10100 #
b10100 )
b1010 "
b1010 (
b1010 &
#32
0$
0%
#33
1$
1%
b10110 #
b10110 )
b1011 "
b1011 (
b1011 &
#35
0$
0%
#36
1$
1%
b11000 #
b11000 )
b1100 "
b1100 (
b1100 &
#38
0$
0%
#39
1$
1%
b11010 #
b11010 )
b1101 "
b1101 (
b1101 &
#41
0$
0%
#42
1$
1%
b11100 #
b11100 )
b1110 "
b1110 (
b1110 &
#44
0$
0%
#45
1$
1%
b11110 #
b11110 )
b1111 "
b1111 (
b1111 &
#47
0$
0%
#48
1$
1%
b100000 #
b100000 )
b10000 "
b10000 (
b10000 &
#50
0$
0%
#51
1$
1%
b100010 #
b100010 )
b10001 "
b10001 (
b10001 &
#53
0$
0%
#54
1$
1%
b100100 #
b100100 )
b10010 "
b10010 (
b10010 &
#56
0$
0%
#57
1$
1%
b100110 #
b100110 )
b10011 "
b10011 (
b10011 &
#59
0$
0%
#60
1$
1%
b101000 #
b101000 )
b10100 "
b10100 (
b10100 &
#62
0$
0%
#63
1$
1%
b101010 #
b101010 )
b10101 "
b10101 (
b10101 &
#65
0$
0%
#66
1$
1%
b101100 #
b101100 )
b10110 "
b10110 (
b10110 &
#68
0$
0%
#69
1$
1%
b101110 #
b101110 )
b10111 "
b10111 (
b10111 &
#71
0$
0%
#72
1$
1%
b110000 #
b110000 )
b11000 "
b11000 (
b11000 &
#74
0$
0%
#75
1$
1%
b110010 #
b110010 )
b11001 "
b11001 (
b11001 &
#77
0$
0%
#78
1$
1%
b110100 #
b110100 )
b11010 "
b11010 (
b11010 &
#80
0$
0%
#81
1$
1%
b110110 #
b110110 )
b11011 "
b11011 (
b11011 &
#83
0$
0%
#84
1$
1%
b111000 #
b111000 )
b11100 "
b11100 (
b11100 &
#86
0$
0%
#87
1$
1%
b111010 #
b111010 )
b11101 "
b11101 (
b11101 &
#89
0$
0%
#90
1$
1%
b111100 #
b111100 )
b11110 "
b11110 (
b11110 &
#92
0$
0%
#93
1$
1%
b111110 #
b111110 )
b11111 "
b11111 (
b11111 &
#95
0$
0%
#96
1$
1%
b1000000 #
b1000000 )
b100000 "
b100000 (
b100000 &
#98
0$
0%
#99
1$
1%
b1000010 #
b1000010 )
b100001 "
b100001 (
b100001 &
#101
0$
0%
#102
1$
1%
b1000100 #
b1000100 )
b100010 "
b100010 (
b100010 &
#104
0$
0%
#105
1$
1%
b1000110 #
b1000110 )
b100011 "
b100011 (
b100011 &
#107
0$
0%
#108
1$
1%
b1001000 #
b1001000 )
b100100 "
b100100 (
b100100 &
#110
0$
0%
#111
1$
1%
b1001010 #
b1001010 )
b100101 "
b100101 (
b100101 &
#113
0$
0%
#114
1$
1%
b1001100 #
b1001100 )
b100110 "
b100110 (
b100110 &
#116
0$
0%
#117
1$
1%
b1001110 #
b1001110 )
b100111 "
b100111 (
b100111 &
#119
0$
0%
#120
1$
1%
b1010000 #
b1010000 )
b101000 "
b101000 (
b101000 &
#122
0$
0%
#123
1$
1%
b1010010 #
b1010010 )
b101001 "
b101001 (
b101001 &
#125
0$
0%
#126
1$
1%
b1010100 #
b1010100 )
b101010 "
b101010 (
b101010 &
#128
0$
0%
#129
1$
1%
b1010110 #
b1010110 )
b101011 "
b101011 (
b101011 &
#131
0$
0%
#132
1$
1%
b1011000 #
b1011000 )
b101100 "
b101100 (
b101100 &
#134
0$
0%
#135
1$
1%
b1011010 #
b1011010 )
b101101 "
b101101 (
b101101 &
#137
0$
0%
#138
1$
1%
b1011100 #
b1011100 )
b101110 "
b101110 (
b101110 &
#140
0$
0%
#141
1$
1%
b1011110 #
b1011110 )
b101111 "
b101111 (
b101111 &
#143
0$
0%
#144
1$
1%
b1100000 #
b1100000 )
b110000 "
b110000 (
b110000 &
#146
0$
0%
#147
1$
1%
b1100010 #
b1100010 )
b110001 "
b110001 (
b110001 &
#149
0$
0%
#150
1$
1%
b1100100 #
b1100100 )
b110010 "
b110010 (
b110010 &
#152
0$
0%
#153
1$
1%
b1100110 #
b1100110 )
b110011 "
b110011 (
b110011 &
#155
0$
0%
#156
1$
1%
b1101000 #
b1101000 )
b110100 "
b110100 (
b110100 &
#158
0$
0%
#159
1$
1%
b1101010 #
b1101010 )
b110101 "
b110101 (
b110101 &
#161
0$
0%
#162
1$
1%
b1101100 #
b1101100 )
b110110 "
b110110 (
b110110 &
#164
0$
0%
#165
1$
1%
b1101110 #
b1101110 )
b110111 "
b110111 (
b110111 &
#167
0$
0%
#168
1$
1%
b1110000 #
b1110000 )
b111000 "
b111000 (
b111000 &
#170
0$
0%
#171
1$
1%
b1110010 #
b1110010 )
b111001 "
b111001 (
b111001 &
#173
0$
0%
#174
1$
1%
b1110100 #
b1110100 )
b111010 "
b111010 (
b111010 &
#176
0$
0%
#177
1$
1%
b1110110 #
b1110110 )
b111011 "
b111011 (
b111011 &
#179
0$
0%
#180
1$
1%
b1111000 #
b1111000 )
b111100 "
b111100 (
b111100 &
#182
0$
0%
#183
1$
1%
b1111010 #
b1111010 )
b111101 "
b111101 (
b111101 &
#185
0$
0%
#186
1$
1%
b1111100 #
b1111100 )
b111110 "
b111110 (
b111110 &
#188
0$
0%
#189
1$
1%
b1111110 #
b1111110 )
b111111 "
b111111 (
b111111 &
#191
0$
0%
#192
1$
1%
b10000000 #
b10000000 )
b1000000 "
b1000000 (
b1000000 &
#194
0$
0%
#195
1$
1%
b10000010 #
b10000010 )
b1000001 "
b1000001 (
b1000001 &
#197
0$
0%
#198
1$
1%
b10000100 #
b10000100 )
b1000010 "
b1000010 (
b1000010 &
#200
0$
0%
#201
1$
1%
b10000110 #
b10000110 )
b1000011 "
b1000011 (
b1000011 &
#203
0$
0%
#204
1$
1%
b10001000 #
b10001000 )
b1000100 "
b1000100 (
b1000100 &
#206
0$
0%
#207
1$
1%
b10001010 #
b10001010 )
b1000101 "
b1000101 (
b1000101 &
#209
0$
0%
#210
1$
1%
b10001100 #
b10001100 )
b1000110 "
b1000110 (
b1000110 &
#212
0$
0%
#213
1$
1%
b10001110 #
b10001110 )
b1000111 "
b1000111 (
b1000111 &
#215
0$
0%
#216
1$
1%
b10010000 #
b10010000 )
b1001000 "
b1001000 (
b1001000 &
#218
0$
0%
#219
1$
1%
b10010010 #
b10010010 )
b1001001 "
b1001001 (
b1001001 &
#221
0$
0%
#222
1$
1%
b10010100 #
b10010100 )
b1001010 "
b1001010 (
b1001010 &
#224
0$
0%
#225
1$
1%
b10010110 #
b10010110 )
b1001011 "
b1001011 (
b1001011 &
#227
0$
0%
#228
1$
1%
b10011000 #
b10011000 )
b1001100 "
b1001100 (
b1001100 &
#230
0$
0%
#231
1$
1%
b10011010 #
b10011010 )
b1001101 "
b1001101 (
b1001101 &
#233
0$
0%
#234
1$
1%
b10011100 #
b10011100 )
b1001110 "
b1001110 (
b1001110 &
#236
0$
0%
#237
1$
1%
b10011110 #
b10011110 )
b1001111 "
b1001111 (
b1001111 &
#239
0$
0%
#240
1$
1%
b10100000 #
b10100000 )
b1010000 "
b1010000 (
b1010000 &
#242
0$
0%
#243
1$
1%
b10100010 #
b10100010 )
b1010001 "
b1010001 (
b1010001 &
#245
0$
0%
#246
1$
1%
b10100100 #
b10100100 )
b1010010 "
b1010010 (
b1010010 &
#248
0$
0%
#249
1$
1%
b10100110 #
b10100110 )
b1010011 "
b1010011 (
b1010011 &
#251
0$
0%
#252
1$
1%
b10101000 #
b10101000 )
b1010100 "
b1010100 (
b1010100 &
#254
0$
0%
#255
1$
1%
b10101010 #
b10101010 )
b1010101 "
b1010101 (
b1010101 &
#257
0$
0%
#258
1$
1%
b10101100 #
b10101100 )
b1010110 "
b1010110 (
b1010110 &
#260
0$
0%
#261
1$
1%
b10101110 #
b10101110 )
b1010111 "
b1010111 (
b1010111 &
#263
0$
0%
#264
1$
1%
b10110000 #
b10110000 )
b1011000 "
b1011000 (
b1011000 &
#266
0$
0%
#267
1$
1%
b10110010 #
b10110010 )
b1011001 "
b1011001 (
b1011001 &
#269
0$
0%
#270
1$
1%
b10110100 #
b10110100 )
b1011010 "
b1011010 (
b1011010 &
#272
0$
0%
#273
1$
1%
b10110110 #
b10110110 )
b1011011 "
b1011011 (
b1011011 &
#275
0$
0%
#276
1$
1%
b10111000 #
b10111000 )
b1011100 "
b1011100 (
b1011100 &
#278
0$
0%
#279
1$
1%
b10111010 #
b10111010 )
b1011101 "
b1011101 (
b1011101 &
#281
0$
0%
#282
1$
1%
b10111100 #
b10111100 )
b1011110 "
b1011110 (
b1011110 &
#284
0$
0%
#285
1$
1%
b10111110 #
b10111110 )
b1011111 "
b1011111 (
b1011111 &
#287
0$
0%
#288
1$
1%
b11000000 #
b11000000 )
b1100000 "
b1100000 (
b1100000 &
#290
0$
0%
#291
1$
1%
b11000010 #
b11000010 )
b1100001 "
b1100001 (
b1100001 &
#293
0$
0%
#294
1$
1%
b11000100 #
b11000100 )
b1100010 "
b1100010 (
b1100010 &
#296
0$
0%
#297
1$
1%
b11000110 #
b11000110 )
b1100011 "
b1100011 (
b1100011 &
#299
0$
0%
#300
1$
1%
b11001000 #
b11001000 )
b1100100 "
b1100100 (
b1100100 &
#302
0$
0%
#303
1$
1%
b11001010 #
b11001010 )
b1100101 "
b1100101 (
b1100101 &
#305
0$
0%
#306
1$
1%
b11001100 #
b11001100 )
b1100110 "
b1100110 (
b1100110 &
#308
0$
0%
#309
1$
1%
b11001110 #
b11001110 )
b1100111 "
b1100111 (
b1100111 &
#311
0$
0%
#312
1$
1%
b11010000 #
b11010000 )
b1101000 "
b1101000 (
b1101000 &
#314
0$
0%
#315
1$
1%
b11010010 #
b11010010 )
b1101001 "
b1101001 (
b1101001 &
#317
0$
0%
#318
1$
1%
b11010100 #
b11010100 )
b1101010 "
b1101010 (
b1101010 &
#320
0$
0%
#321
1$
1%
b11010110 #
b11010110 )
b1101011 "
b1101011 (
b1101011 &
#323
0$
0%
#324
1$
1%
b11011000 #
b11011000 )
b1101100 "
b1101100 (
b1101100 &
#326
0$
0%
#327
1$
1%
b11011010 #
b11011010 )
b1101101 "
b1101101 (
b1101101 &
#329
0$
0%
#330
1$
1%
b11011100 #
b11011100 )
b1101110 "
b1101110 (
b1101110 &
#332
0$
0%
#333
1$
1%
b11011110 #
b11011110 )
b1101111 "
b1101111 (
b1101111 &
#335
0$
0%
#336
1$
1%
b11100000 #
b11100000 )
b1110000 "
b1110000 (
b1110000 &
#338
0$
0%
#339
1$
1%
b11100010 #
b11100010 )
b1110001 "
b1110001 (
b1110001 &
#341
0$
0%
#342
1$
1%
b11100100 #
b11100100 )
b1110010 "
b1110010 (
b1110010 &
#344
0$
0%
#345
1$
1%
b11100110 #
b11100110 )
b1110011 "
b1110011 (
b1110011 &
#347
0$
0%
#348
1$
1%
b11101000 #
b11101000 )
b1110100 "
b1110100 (
b1110100 &
#350
0$
0%
#351
1$
1%
b11101010 #
b11101010 )
b1110101 "
b1110101 (
b1110101 &
#353
0$
0%
#354
1$
1%
b11101100 #
b11101100 )
b1110110 "
b1110110 (
b1110110 &
#356
0$
0%
#357
1$
1%
b11101110 #
b11101110 )
b1110111 "
b1110111 (
b1110111 &
#359
0$
0%
#360
1$
1%
b11110000 #
b11110000 )
b1111000 "
b1111000 (
b1111000 &
#362
0$
0%
#363
1$
1%
b11110010 #
b11110010 )
b1111001 "
b1111001 (
b1111001 &
#365
0$
0%
#366
1$
1%
b11110100 #
b11110100 )
b1111010 "
b1111010 (
b1111010 &
#368
0$
0%
#369
1$
1%
b11110110 #
b11110110 )
b1111011 "
b1111011 (
b1111011 &
#371
0$
0%
#372
1$
1%
b11111000 #
b11111000 )
b1111100 "
b1111100 (
b1111100 &
#374
0$
0%
#375
1$
1%
b11111010 #
b11111010 )
b1111101 "
b1111101 (
b1111101 &
#377
0$
0%
#378
1$
1%
b11111100 #
b11111100 )
b1111110 "
b1111110 (
b1111110 &
#380
0$
0%
#381
1$
1%
b11111110 #
b11111110 )
b1111111 "
b1111111 (
b1111111 &
#383
0$
0%
#384
1$
1%
b0 #
b0 )
b10000000 "
b10000000 (
b10000000 &
#386
0$
0%
#387
1$
1%
b10 #
b10 )
b10000001 "
b10000001 (
b10000001 &
#389
0$
0%
#390
1$
1%
b100 #
b100 )
b10000010 "
b10000010 (
b10000010 &
#392
0$
0%
#393
1$
1%
b110 #
b110 )
b10000011 "
b10000011 (
b10000011 &
#395
0$
0%
#396
1$
1%
b1000 #
b1000 )
b10000100 "
b10000100 (
b10000100 &
#398
0$
0%
#399
1$
1%
b1010 #
b1010 )
b10000101 "
b10000101 (
b10000101 &
#401
0$
0%
#402
1$
1%
b1100 #
b1100 )
b10000110 "
b10000110 (
b10000110 &
#404
0$
0%
#405
1$
1%
b1110 #
b1110 )
b10000111 "
b10000111 (
b10000111 &
#407
0$
0%
#408
1$
1%
b10000 #
b10000 )
b10001000 "
b10001000 (
b10001000 &
#410
0$
0%
#411
1$
1%
b10010 #
b10010 )
b10001001 "
b10001001 (
b10001001 &
#413
0$
0%
#414
1$
1%
b10100 #
b10100 )
b10001010 "
b10001010 (
b10001010 &
#416
0$
0%
#417
1$
1%
b10110 #
b10110 )
b10001011 "
b10001011 (
b10001011 &
#419
0$
0%
#420
1$
1%
b11000 #
b11000 )
b10001100 "
b10001100 (
b10001100 &
#422
0$
0%
#423
1$
1%
b11010 #
b11010 )
b10001101 "
b10001101 (
b10001101 &
#425
0$
0%
#426
1$
1%
b11100 #
b11100 )
b10001110 "
b10001110 (
b10001110 &
#428
0$
0%
#429
1$
1%
b11110 #
b11110 )
b10001111 "
b10001111 (
b10001111 &
#431
0$
0%
#432
1$
1%
b100000 #
b100000 )
b10010000 "
b10010000 (
b10010000 &
#434
0$
0%
#435
1$
1%
b100010 #
b100010 )
b10010001 "
b10010001 (
b10010001 &
#437
0$
0%
#438
1$
1%
b100100 #
b100100 )
b10010010 "
b10010010 (
b10010010 &
#440
0$
0%
#441
1$
1%
b100110 #
b100110 )
b10010011 "
b10010011 (
b10010011 &
#443
0$
0%
#444
1$
1%
b101000 #
b101000 )
b10010100 "
b10010100 (
b10010100 &
#446
0$
0%
#447
1$
1%
b101010 #
b101010 )
b10010101 "
b10010101 (
b10010101 &
#449
0$
0%
#450
1$
1%
b101100 #
b101100 )
b10010110 "
b10010110 (
b10010110 &
#452
0$
0%
#453
1$
1%
b101110 #
b101110 )
b10010111 "
b10010111 (
b10010111 &
#455
0$
0%
#456
1$
1%
b110000 #
b110000 )
b10011000 "
b10011000 (
b10011000 &
#458
0$
0%
#459
1$
1%
b110010 #
b110010 )
b10011001 "
b10011001 (
b10011001 &
#461
0$
0%
#462
1$
1%
b110100 #
b110100 )
b10011010 "
b10011010 (
b10011010 &
#464
0$
0%
#465
1$
1%
b110110 #
b110110 )
b10011011 "
b10011011 (
b10011011 &
#467
0$
0%
#468
1$
1%
b111000 #
b111000 )
b10011100 "
b10011100 (
b10011100 &
#470
0$
0%
#471
1$
1%
b111010 #
b111010 )
b10011101 "
b10011101 (
b10011101 &
#473
0$
0%
#474
1$
1%
b111100 #
b111100 )
b10011110 "
b10011110 (
b10011110 &
#476
0$
0%
#477
1$
1%
b111110 #
b111110 )
b10011111 "
b10011111 (
b10011111 &
#479
0$
0%
#480
1$
1%
b1000000 #
b1000000 )
b10100000 "
b10100000 (
b10100000 &
#482
0$
0%
#483
1$
1%
b1000010 #
b1000010 )
b10100001 "
b10100001 (
b10100001 &
#485
0$
0%
#486
1$
1%
b1000100 #
b1000100 )
b10100010 "
b10100010 (
b10100010 &
#488
0$
0%
#489
1$
1%
b1000110 #
b1000110 )
b10100011 "
b10100011 (
b10100011 &
#491
0$
0%
#492
1$
1%
b1001000 #
b1001000 )
b10100100 "
b10100100 (
b10100100 &
#494
0$
0%
#495
1$
1%
b1001010 #
b1001010 )
b10100101 "
b10100101 (
b10100101 &
#497
0$
0%
#498
1$
1%
b1001100 #
b1001100 )
b10100110 "
b10100110 (
b10100110 &
#500
0$
0%
#501
1$
1%
b1001110 #
b1001110 )
b10100111 "
b10100111 (
b10100111 &
#503
0$
0%
#504
1$
1%
b1010000 #
b1010000 )
b10101000 "
b10101000 (
b10101000 &
#506
0$
0%
#507
1$
1%
b1010010 #
b1010010 )
b10101001 "
b10101001 (
b10101001 &
#509
0$
0%
#510
1$
1%
b1010100 #
b1010100 )
b10101010 "
b10101010 (
b10101010 &
#512
0$
0%
#513
1$
1%
b1010110 #
b1010110 )
b10101011 "
b10101011 (
b10101011 &
#515
0$
0%
#516
1$
1%
b1011000 #
b1011000 )
b10101100 "
b10101100 (
b10101100 &
#518
0$
0%
#519
1$
1%
b1011010 #
b1011010 )
b10101101 "
b10101101 (
b10101101 &
#521
0$
0%
#522
1$
1%
b1011100 #
b1011100 )
b10101110 "
b10101110 (
b10101110 &
#524
0$
0%
#525
1$
1%
b1011110 #
b1011110 )
b10101111 "
b10101111 (
b10101111 &
#527
0$
0%
#528
1$
1%
b1100000 #
b1100000 )
b10110000 "
b10110000 (
b10110000 &
#530
0$
0%
#531
1$
1%
b1100010 #
b1100010 )
b10110001 "
b10110001 (
b10110001 &
#533
0$
0%
#534
1$
1%
b1100100 #
b1100100 )
b10110010 "
b10110010 (
b10110010 &
#536
0$
0%
#537
1$
1%
b1100110 #
b1100110 )
b10110011 "
b10110011 (
b10110011 &
#539
0$
0%
#540
1$
1%
b1101000 #
b1101000 )
b10110100 "
b10110100 (
b10110100 &
#542
0$
0%
#543
1$
1%
b1101010 #
b1101010 )
b10110101 "
b10110101 (
b10110101 &
#545
0$
0%
#546
1$
1%
b1101100 #
b1101100 )
b10110110 "
b10110110 (
b10110110 &
#548
0$
0%
#549
1$
1%
b1101110 #
b1101110 )
b10110111 "
b10110111 (
b10110111 &
#551
0$
0%
#552
1$
1%
b1110000 #
b1110000 )
b10111000 "
b10111000 (
b10111000 &
#554
0$
0%
#555
1$
1%
b1110010 #
b1110010 )
b10111001 "
b10111001 (
b10111001 &
#557
0$
0%
#558
1$
1%
b1110100 #
b1110100 )
b10111010 "
b10111010 (
b10111010 &
#560
0$
0%
#561
1$
1%
b1110110 #
b1110110 )
b10111011 "
b10111011 (
b10111011 &
#563
0$
0%
#564
1$
1%
b1111000 #
b1111000 )
b10111100 "
b10111100 (
b10111100 &
#566
0$
0%
#567
1$
1%
b1111010 #
b1111010 )
b10111101 "
b10111101 (
b10111101 &
#569
0$
0%
#570
1$
1%
b1111100 #
b1111100 )
b10111110 "
b10111110 (
b10111110 &
#572
0$
0%
#573
1$
1%
b1111110 #
b1111110 )
b10111111 "
b10111111 (
b10111111 &
#575
0$
0%
#576
1$
1%
b10000000 #
b10000000 )
b11000000 "
b11000000 (
b11000000 &
#578
0$
0%
#579
1$
1%
b10000010 #
b10000010 )
b11000001 "
b11000001 (
b11000001 &
#581
0$
0%
#582
1$
1%
b10000100 #
b10000100 )
b11000010 "
b11000010 (
b11000010 &
#584
0$
0%
#585
1$
1%
b10000110 #
b10000110 )
b11000011 "
b11000011 (
b11000011 &
#587
0$
0%
#588
1$
1%
b10001000 #
b10001000 )
b11000100 "
b11000100 (
b11000100 &
#590
0$
0%
#591
1$
1%
b10001010 #
b10001010 )
b11000101 "
b11000101 (
b11000101 &
#593
0$
0%
#594
1$
1%
b10001100 #
b10001100 )
b11000110 "
b11000110 (
b11000110 &
#596
0$
0%
#597
1$
1%
b10001110 #
b10001110 )
b11000111 "
b11000111 (
b11000111 &
#599
0$
0%
#600
1$
1%
b10010000 #
b10010000 )
b11001000 "
b11001000 (
b11001000 &
#602
0$
0%
#603
1$
1%
b10010010 #
b10010010 )
b11001001 "
b11001001 (
b11001001 &
#605
0$
0%
#606
1$
1%
b10010100 #
b10010100 )
b11001010 "
b11001010 (
b11001010 &
#608
0$
0%
#609
1$
1%
b10010110 #
b10010110 )
b11001011 "
b11001011 (
b11001011 &
#611
0$
0%
#612
1$
1%
b10011000 #
b10011000 )
b11001100 "
b11001100 (
b11001100 &
#614
0$
0%
#615
1$
1%
b10011010 #
b10011010 )
b11001101 "
b11001101 (
b11001101 &
#617
0$
0%
#618
1$
1%
b10011100 #
b10011100 )
b11001110 "
b11001110 (
b11001110 &
#620
0$
0%
#621
1$
1%
b10011110 #
b10011110 )
b11001111 "
b11001111 (
b11001111 &
#623
0$
0%
#624
1$
1%
b10100000 #
b10100000 )
b11010000 "
b11010000 (
b11010000 &
#626
0$
0%
#627
1$
1%
b10100010 #
b10100010 )
b11010001 "
b11010001 (
b11010001 &
#629
0$
0%
#630
1$
1%
b10100100 #
b10100100 )
b11010010 "
b11010010 (
b11010010 &
#632
0$
0%
#633
1$
1%
b10100110 #
b10100110 )
b11010011 "
b11010011 (
b11010011 &
#635
0$
0%
#636
1$
1%
b10101000 #
b10101000 )
b11010100 "
b11010100 (
b11010100 &
#638
0$
0%
#639
1$
1%
b10101010 #
b10101010 )
b11010101 "
b11010101 (
b11010101 &
#641
0$
0%
#642
1$
1%
b10101100 #
b10101100 )
b11010110 "
b11010110 (
b11010110 &
#644
0$
0%
#645
1$
1%
b10101110 #
b10101110 )
b11010111 "
b11010111 (
b11010111 &
#647
0$
0%
#648
1$
1%
b10110000 #
b10110000 )
b11011000 "
b11011000 (
b11011000 &
#650
0$
0%
#651
1$
1%
b10110010 #
b10110010 )
b11011001 "
b11011001 (
b11011001 &
#653
0$
0%
#654
1$
1%
b10110100 #
b10110100 )
b11011010 "
b11011010 (
b11011010 &
#656
0$
0%
#657
1$
1%
b10110110 #
b10110110 )
b11011011 "
b11011011 (
b11011011 &
#659
0$
0%
#660
1$
1%
b10111000 #
b10111000 )
b11011100 "
b11011100 (
b11011100 &
#662
0$
0%
#663
1$
1%
b10111010 #
b10111010 )
b11011101 "
b11011101 (
b11011101 &
#665
0$
0%
#666
1$
1%
b10111100 #
b10111100 )
b11011110 "
b11011110 (
b11011110 &
#668
0$
0%
#669
1$
1%
b10111110 #
b10111110 )
b11011111 "
b11011111 (
b11011111 &
#671
0$
0%
#672
1$
1%
b11000000 #
b11000000 )
b11100000 "
b11100000 (
b11100000 &
#674
0$
0%
#675
1$
1%
b11000010 #
b11000010 )
b11100001 "
b11100001 (
b11100001 &
#677
0$
0%
#678
1$
1%
b11000100 #
b11000100 )
b11100010 "
b11100010 (
b11100010 &
#680
0$
0%
#681
1$
1%
b11000110 #
b11000110 )
b11100011 "
b11100011 (
b11100011 &
#683
0$
0%
#684
1$
1%
b11001000 #
b11001000 )
b11100100 "
b11100100 (
b11100100 &
#686
0$
0%
#687
1$
1%
b11001010 #
b11001010 )
b11100101 "
b11100101 (
b11100101 &
#689
0$
0%
#690
1$
1%
b11001100 #
b11001100 )
b11100110 "
b11100110 (
b11100110 &
#692
0$
0%
#693
1$
1%
b11001110 #
b11001110 )
b11100111 "
b11100111 (
b11100111 &
#695
0$
0%
#696
1$
1%
b11010000 #
b11010000 )
b11101000 "
b11101000 (
b11101000 &
#698
0$
0%
#699
1$
1%
b11010010 #
b11010010 )
b11101001 "
b11101001 (
b11101001 &
#701
0$
0%
#702
1$
1%
b11010100 #
b11010100 )
b11101010 "
b11101010 (
b11101010 &
#704
0$
0%
#705
1$
1%
b11010110 #
b11010110 )
b11101011 "
b11101011 (
b11101011 &
#707
0$
0%
#708
1$
1%
b11011000 #
b11011000 )
b11101100 "
b11101100 (
b11101100 &
#710
0$
0%
#711
1$
1%
b11011010 #
b11011010 )
b11101101 "
b11101101 (
b11101101 &
#713
0$
0%
#714
1$
1%
b11011100 #
b11011100 )
b11101110 "
b11101110 (
b11101110 &
#716
0$
0%
#717
1$
1%
b11011110 #
b11011110 )
b11101111 "
b11101111 (
b11101111 &
#719
0$
0%
#720
1$
1%
b11100000 #
b11100000 )
b11110000 "
b11110000 (
b11110000 &
#722
0$
0%
#723
1$
1%
b11100010 #
b11100010 )
b11110001 "
b11110001 (
b11110001 &
#725
0$
0%
#726
1$
1%
b11100100 #
b11100100 )
b11110010 "
b11110010 (
b11110010 &
#728
0$
0%
#729
1$
1%
b11100110 #
b11100110 )
b11110011 "
b11110011 (
b11110011 &
#731
0$
0%
#732
1$
1%
b11101000 #
b11101000 )
b11110100 "
b11110100 (
b11110100 &
#734
0$
0%
#735
1$
1%
b11101010 #
b11101010 )
b11110101 "
b11110101 (
b11110101 &
#737
0$
0%
#738
1$
1%
b11101100 #
b11101100 )
b11110110 "
b11110110 (
b11110110 &
#740
0$
0%
#741
1$
1%
b11101110 #
b11101110 )
b11110111 "
b11110111 (
b11110111 &
#743
0$
0%
#744
1$
1%
b11110000 #
b11110000 )
b11111000 "
b11111000 (
b11111000 &
#746
0$
0%
#747
1$
1%
b11110010 #
b11110010 )
b11111001 "
b11111001 (
b11111001 &
#749
0$
0%
#750
1$
1%
b11110100 #
b11110100 )
b11111010 "
b11111010 (
b11111010 &
#752
0$
0%
#753
1$
1%
b11110110 #
b11110110 )
b11111011 "
b11111011 (
b11111011 &
#755
0$
0%
#756
1$
1%
b11111000 #
b11111000 )
b11111100 "
b11111100 (
b11111100 &
#758
0$
0%
#759
1$
1%
b11111010 #
b11111010 )
b11111101 "
b11111101 (
b11111101 &
#761
0$
0%
#762
1$
1%
b11111100 #
b11111100 )
b11111110 "
b11111110 (
b11111110 &
#764
0$
0%
#765
1$
1%
b11111110 #
b11111110 )
b11111111 "
b11111111 (
b11111111 &
#767
0$
0%
#768
1$
1%
b0 #
b0 )
b100000000 "
b100000000 (
b100000000 &
#770
0$
0%
#771
1$
1%
b10 #
b10 )
b100000001 "
b100000001 (
b100000001 &
#773
0$
0%
#774
1$
1%
b100 #
b100 )
b100000010 "
b100000010 (
b100000010 &
#776
0$
0%
#777
1$
1%
b110 #
b110 )
b100000011 "
b100000011 (
b100000011 &
#779
0$
0%
#780
1$
1%
b1000 #
b1000 )
b100000100 "
b100000100 (
b100000100 &
#782
0$
0%
#783
1$
1%
b1010 #
b1010 )
b100000101 "
b100000101 (
b100000101 &
#785
0$
0%
#786
1$
1%
b1100 #
b1100 )
b100000110 "
b100000110 (
b100000110 &
#788
0$
0%
#789
1$
1%
b1110 #
b1110 )
b100000111 "
b100000111 (
b100000111 &
#791
0$
0%
#792
1$
1%
b10000 #
b10000 )
b100001000 "
b100001000 (
b100001000 &
#794
0$
0%
#795
1$
1%
b10010 #
b10010 )
b100001001 "
b100001001 (
b100001001 &
#797
0$
0%
#798
1$
1%
b10100 #
b10100 )
b100001010 "
b100001010 (
b100001010 &
#800
0$
0%
#801
1$
1%
b10110 #
b10110 )
b100001011 "
b100001011 (
b100001011 &
#803
0$
0%
#804
1$
1%
b11000 #
b11000 )
b100001100 "
b100001100 (
b100001100 &
#806
0$
0%
#807
1$
1%
b11010 #
b11010 )
b100001101 "
b100001101 (
b100001101 &
#809
0$
0%
#810
1$
1%
b11100 #
b11100 )
b100001110 "
b100001110 (
b100001110 &
#812
0$
0%
