pipeline/pipeline.v
module pipeline(
  zout,rs1,rs2,rd,func,addr,clk1,clk2
);
input[3:0] rs1,rs2,rd,func;
input[7:0] addr;
input clk1,clk2;
output[15:0] zout;

reg[15:0] l12_a,l12_b,l23_z,l34_z;
reg[3:0] l12_rd,l12_func,l23_rd;
reg[7:0] l12_addr,l23_addr,l34_addr;

reg[15:0]regbank[0:15];
reg[15:0]mem[0:255];

assign zout=l34_z;

always @(posedge clk1) begin ///stage 1
  l12_a <=  #2 regbank[rs1];
  l12_b <=  #2 regbank[rs2];
  l12_rd <= #2 rd;
  l12_func <= #2 func;
  l12_addr <= #2 addr;

end

always @(negedge clk2) begin // stage 2
  case (l12_func)
    0 : l23_z <= #2 l12_a + l12_b;
    1 : l23_z <= #2 l12_a - l12_b;
    2 : l23_z <= #2 l12_a * l12_b;
    3 : l23_z <= #2 l12_a;
    4 : l23_z <= #2 l12_b;
    5 : l23_z <= #2 l12_a & l12_b;
    6 : l23_z <= #2 l12_a | l12_b;
    7 : l23_z <= #2 l12_a ^ l12_b;
    8 : l23_z <= #2 -l12_a;
    9 : l23_z <= #2 -l12_b;
    10: l23_z <= #2 l12_a >> 1;
    11: l23_z <= #2 l12_a << 1;
    default: l23_z <= #2 16'hxxxx;
  endcase
  l23_addr <= #2 l12_addr;
  l23_rd   <= #2 l12_rd;
end

always @(posedge clk1) begin // stage 3
  regbank[l23_rd] <= #2 l23_z;
  l34_z   <= #2 l23_z;
  l34_addr <= #2 l23_addr;
end

always @(negedge clk2) begin /// stage 4
  mem[l34_addr] <= #2 l34_z;
end

endmodule

pipeline/tb.v
module tb();

  wire [15:0] z;
  reg [3:0] rs1, rs2, rd, func;
  reg [7:0] addr;
  reg clk1, clk2;
  integer k;

  // Instantiate the DUT (Design Under Test)
  pipeline dut(z, rs1, rs2, rd, func, addr, clk1, clk2);

  // Generate clocks
  initial begin
    clk1 = 0; clk2 = 0;
    repeat(20) begin
      #5 clk1 = 1; #5 clk1 = 0;
      #5 clk2 = 1; #5 clk2 = 0;
    end
  end

  // Initialize register bank
  initial begin
    for (k = 0; k < 16; k = k + 1)
      dut.regbank[k] = k;
  end

  // Stimulus
  initial begin
    #5  rs1=1;  rs2=5;  rd=10; func=0;  addr=125; // ADD
    #20 rs1=3;  rs2=8;  rd=12; func=2;  addr=126; // MUL
    #20 rs1=10; rs2=5;  rd=14; func=1;  addr=128; // SUB
    #20 rs1=7;  rs2=3;  rd=13; func=11; addr=127; // SLA (shift left)
    #20 rs1=10; rs2=5;  rd=15; func=1;  addr=129; // SUB
    #20 rs1=12; rs2=13; rd=0;  func=0;  addr=130; // ADD (changed rd=16 → rd=0)
  end

  // Display memory contents after sufficient delay
  initial begin
    #220;
    $display("\n--- Memory Contents ---");
    for (k = 125; k <= 130; k = k + 1)
      $display("mem[%3d] = %3d", k, dut.mem[k]);
  end

  // Dump waveforms
  initial begin
    $dumpfile("pipeline.vcd");
    $dumpvars(0, tb);
    $monitor("Time: %3d | zout = %3d", $time, z);
    #300 $finish;
  end

endmodule

pipeline/pipeline.vcd
$date
	Wed Jul 16 19:30:04 2025
$end
$version
	Icarus Verilog
$end
$timescale
	1s
$end
$scope module tb $end
$var wire 16 ! z [15:0] $end
$var reg 8 " addr [7:0] $end
$var reg 1 # clk1 $end
$var reg 1 $ clk2 $end
$var reg 4 % func [3:0] $end
$var reg 4 & rd [3:0] $end
$var reg 4 ' rs1 [3:0] $end
$var reg 4 ( rs2 [3:0] $end
$var integer 32 ) k [31:0] $end
$scope module dut $end
$var wire 8 * addr [7:0] $end
$var wire 1 # clk1 $end
$var wire 1 $ clk2 $end
$var wire 4 + func [3:0] $end
$var wire 4 , rd [3:0] $end
$var wire 4 - rs1 [3:0] $end
$var wire 4 . rs2 [3:0] $end
$var wire 16 / zout [15:0] $end
$var reg 16 0 l12_a [15:0] $end
$var reg 8 1 l12_addr [7:0] $end
$var reg 16 2 l12_b [15:0] $end
$var reg 4 3 l12_func [3:0] $end
$var reg 4 4 l12_rd [3:0] $end
$var reg 8 5 l23_addr [7:0] $end
$var reg 4 6 l23_rd [3:0] $end
$var reg 16 7 l23_z [15:0] $end
$var reg 8 8 l34_addr [7:0] $end
$var reg 16 9 l34_z [15:0] $end
$upscope $end
$upscope $end
$enddefinitions $end
$comment Show the parameter values. $end
$dumpall
$end
#0
$dumpvars
bx 9
bx 8
bx 7
bx 6
bx 5
bx 4
bx 3
bx 2
bx 1
bx 0
bx /
bx .
bx -
bx ,
bx +
bx *
b10000 )
bx (
bx '
bx &
bx %
0$
0#
bx "
bx !
$end
#5
b1111101 "
b1111101 *
b0 %
b0 +
b1010 &
b1010 ,
b101 (
b101 .
b1 '
b1 -
1#
#7
b1111101 1
b0 3
b1010 4
b101 2
b1 0
#10
0#
#15
1$
#20
0$
#22
b1010 6
b1111101 5
b110 7
#25
1#
b1111110 "
b1111110 *
b10 %
b10 +
b1100 &
b1100 ,
b1000 (
b1000 .
b11 '
b11 -
#27
b1111101 8
b110 !
b110 /
b110 9
b1111110 1
b10 3
b1100 4
b1000 2
b11 0
#30
0#
#35
1$
#40
0$
#42
b1100 6
b1111110 5
b11000 7
#45
1#
b10000000 "
b10000000 *
b1 %
b1 +
b1110 &
b1110 ,
b101 (
b101 .
b1010 '
b1010 -
#47
b10000000 1
b1 3
b1110 4
b101 2
b110 0
b1111110 8
b11000 !
b11000 /
b11000 9
#50
0#
#55
1$
#60
0$
#62
b1110 6
b10000000 5
b1 7
#65
1#
b1111111 "
b1111111 *
b1011 %
b1011 +
b1101 &
b1101 ,
b11 (
b11 .
b111 '
b111 -
#67
b10000000 8
b1 !
b1 /
b1 9
b1111111 1
b1011 3
b1101 4
b11 2
b111 0
#70
0#
#75
1$
#80
0$
#82
b1101 6
b1111111 5
b1110 7
#85
1#
b10000001 "
b10000001 *
b1 %
b1 +
b1111 &
b1111 ,
b101 (
b101 .
b1010 '
b1010 -
#87
b10000001 1
b1 3
b1111 4
b101 2
b110 0
b1111111 8
b1110 !
b1110 /
b1110 9
#90
0#
#95
1$
#100
0$
#102
b1111 6
b10000001 5
b1 7
#105
1#
b10000010 "
b10000010 *
b0 %
b0 +
b0 &
b0 ,
b1101 (
b1101 .
b1100 '
b1100 -
#107
b10000001 8
b1 !
b1 /
b1 9
b10000010 1
b0 3
b0 4
b1110 2
b11000 0
#110
0#
#115
1$
#120
0$
#122
b0 6
b10000010 5
b100110 7
#125
1#
#127
b10000010 8
b100110 !
b100110 /
b100110 9
#130
0#
#135
1$
#140
0$
#145
1#
#150
0#
#155
1$
#160
0$
#165
1#
#170
0#
#175
1$
#180
0$
#185
1#
#190
0#
#195
1$
#200
0$
#205
1#
#210
0#
#215
1$
#220
0$
b10000011 )
