bit_shifter/bit_shifter.v
module bit_shifter(clk,clr,A,E);
    input clk,clr,A;
    output reg E;
    reg B,C,D;
    always @(posedge clk or negedge clr)
    begin
         if(!clr) begin B=0;C=0;D=0;E=0; end
         else begin
              E=D;
              D=C;
              C=B;
              B=A;
        

         end

    end

  
endmodule

bit_shifter/bit_shifter_tb.v
module bit_shifter_tb;
wire E;
reg clk,clr,A;

bit_shifter DUT(clk,clr,A,E);

initial
begin
  clk=1'b0;
  #2 clr=0;
  #5 clr=1;
end


always #5 clk= ~clk;

initial begin
  #2;
  repeat(2)
  begin
    #10 A=0;
    #10 A=0;
    #10 A=1;
    #10 A=1;
  end 
end




initial
begin
  $dumpfile("shifter.vcd");
  $dumpvars(0,bit_shifter_tb);
  #200 $finish;
end


endmodule

bit_shifter/shifter.vcd
$date
	Thu May 29 11:28:26 2025
$end
$version
	Icarus Verilog
$end
$timescale
	1s
$end
$scope module bit_shifter_tb $end
$var wire 1 ! E $end
$var reg 1 " A $end
$var reg 1 # clk $end
$var reg 1 $ clr $end
$scope module DUT $end
$var wire 1 " A $end
$var wire 1 # clk $end
$var wire 1 $ clr $end
$var reg 1 % B $end
$var reg 1 & C $end
$var reg 1 ' D $end
$var reg 1 ! E $end
$upscope $end
$upscope $end
$enddefinitions $end
$comment Show the parameter values. $end
$dumpall
$end
#0
$dumpvars
x'
x&
x%
x$
0#
x"
x!
$end
#2
0!
0'
0&
0%
0$
#5
1#
#7
1$
#10
0#
#12
0"
#15
1#
#20
0#
#25
1#
#30
0#
#32
1"
#35
1%
1#
#40
0#
#45
1&
1#
#50
0#
#52
0"
#55
0%
1'
1#
#60
0#
#65
0&
1!
1#
#70
0#
#72
1"
#75
1%
0'
1#
#80
0#
#85
1&
0!
1#
#90
0#
#95
1'
1#
#100
0#
#105
1!
1#
