parity_generator/parity_gen.v
module parity_gen(clk,x,z);
input clk,x;
output reg z;
parameter even =0,odd=1 ;
reg even_odd;
always @(posedge clk)
  case(even_odd)
  even:even_odd=x?odd:even;
  odd:even_odd=x?even:odd;
  default:even_odd<=even;
  endcase

always @(even_odd)
  case(even_odd)
  even:z=0;
  odd:z=1;
  endcase

endmodule

parity_generator/parity_gen_tb.v
module parity_gen_tb;
reg clk,x;
wire z;
initial begin
  clk=1'b0;
end

parity_gen dut(clk,x,z);

always #5 clk=~clk;

initial begin
  $dumpfile("parity.vcd");
  $dumpvars(0,parity_gen_tb);
  
end

initial begin
  $monitor($time," x=%b z=%b",x,z);
 
  x=0;#10 x=1;#10 x=1;#10 x=1;
  #10 x=0;#10 x=1;#10 x=1;#10 x=1;
  #10 $finish;

end
endmodule

parity_generator/parity.vcd
$date
	Fri May 30 17:09:54 2025
$end
$version
	Icarus Verilog
$end
$timescale
	1s
$end
$scope module parity_gen_tb $end
$var wire 1 ! z $end
$var reg 1 " clk $end
$var reg 1 # x $end
$scope module dut $end
$var wire 1 " clk $end
$var wire 1 # x $end
$var parameter 32 $ even $end
$var parameter 32 % odd $end
$var reg 1 & even_odd $end
$var reg 1 ! z $end
$upscope $end
$upscope $end
$enddefinitions $end
$comment Show the parameter values. $end
$dumpall
b1 %
b0 $
$end
#0
$dumpvars
x&
0#
0"
x!
$end
#5
0!
0&
1"
#10
0"
1#
#15
1!
1&
1"
#20
0"
#25
0!
0&
1"
#30
0"
#35
1!
1&
1"
#40
0"
0#
#45
1"
#50
0"
1#
#55
0!
0&
1"
#60
0"
#65
1!
1&
1"
#70
0"
#75
0!
0&
1"
