counter/bcd_counter.v
module bcd_counter(
  output reg [3:0] count,
  input up,
  input down,
  input clk,
  input reset
);

always @(posedge clk) begin
  if (reset)
    count <= 0;
  else begin
    if (up) begin
      if (count == 9)
        count <= 0;
      else
        count <= count + 1;
    end else if (down) begin
      if (count == 0)
        count <= 9;
      else
        count <= count - 1;
    end
  end
end

endmodule

counter/bcd_counter_tb.v
module bcd_counter_tb();

reg clk = 0, up = 0, down = 0, reset = 0;
wire [3:0] count;

bcd_counter uut(count, up, down, clk, reset);

// Generate clock
always #5 clk = ~clk;

initial begin
  $dumpfile("counter.vcd");
  $dumpvars(0,bcd_counter_tb);

  reset = 1; #10;
  reset = 0;

  up = 1;
  repeat(12) #10;  // Count up past 9

  up = 0;
  down = 1;
  repeat(12) #10;  // Count down past 0

  $finish;
end

endmodule

counter/counter.vcd
$date
	Wed Jul 16 19:45:18 2025
$end
$version
	Icarus Verilog
$end
$timescale
	1s
$end
$scope module bcd_counter_tb $end
$var wire 4 ! count [3:0] $end
$var reg 1 " clk $end
$var reg 1 # down $end
$var reg 1 $ reset $end
$var reg 1 % up $end
$scope module uut $end
$var wire 1 " clk $end
$var wire 1 # down $end
$var wire 1 $ reset $end
$var wire 1 % up $end
$var reg 4 & count [3:0] $end
$upscope $end
$upscope $end
$enddefinitions $end
$comment Show the parameter values. $end
$dumpall
$end
#0
$dumpvars
bx &
0%
1$
0#
0"
bx !
$end
#5
b0 !
b0 &
1"
#10
0"
1%
0$
#15
b1 !
b1 &
1"
#20
0"
#25
b10 !
b10 &
1"
#30
0"
#35
b11 !
b11 &
1"
#40
0"
#45
b100 !
b100 &
1"
#50
0"
#55
b101 !
b101 &
1"
#60
0"
#65
b110 !
b110 &
1"
#70
0"
#75
b111 !
b111 &
1"
#80
0"
#85
b1000 !
b1000 &
1"
#90
0"
#95
b1001 !
b1001 &
1"
#100
0"
#105
b0 !
b0 &
1"
#110
0"
#115
b1 !
b1 &
1"
#120
0"
#125
b10 !
b10 &
1"
#130
0"
1#
0%
#135
b1 !
b1 &
1"
#140
0"
#145
b0 !
b0 &
1"
#150
0"
#155
b1001 !
b1001 &
1"
#160
0"
#165
b1000 !
b1000 &
1"
#170
0"
#175
b111 !
b111 &
1"
#180
0"
#185
b110 !
b110 &
1"
#190
0"
#195
b101 !
b101 &
1"
#200
0"
#205
b100 !
b100 &
1"
#210
0"
#215
b11 !
b11 &
1"
#220
0"
#225
b10 !
b10 &
1"
#230
0"
#235
b1 !
b1 &
1"
#240
0"
#245
b0 !
b0 &
1"
