mul_algo/mul_control.v
module mul_control(lda,ldb,ldp,clrp,decb,done,clk,eqz,start);
input clk,eqz,start;
output reg lda,ldb,ldp,clrp,decb,done;
reg [2:0] state;
parameter s0 =3'b000,s1=3'b001, s2=3'b010,s3=3'b011,s4=3'b100;
always @(posedge clk)
case(state)
   s0:if(start) state<=s1;
   s1:state<=s2;
   s2:state<=s3;
   s3:#2 if(eqz) state<=s4;
   s4: state<=s4;
   default:state<=s0;
endcase


always @(state)
begin
  case(state)
  s0:begin
    #1 lda=0;ldb=0;ldp=0;clrp=0;decb=0;
  end

  s1:begin
    #1 lda=1;
  end

  s2:begin
    #1 lda=0;ldb=1;clrp=1;
  end

  s3:begin
    #1 ldb=0;ldp=1;clrp=0;decb=1;
  end

  s4:begin
    #1 done=1;ldb=0;ldp=0;decb=0;
  end

  default:begin
    #1 lda=0; ldb=0;ldp=0;clrp=0;decb=0;
  end

  endcase
end
endmodule

mul_algo/mul_datapath.v
module mul_datapath(eqz,lda, ldb,ldp,clrp,decb,data_in,clk);
input lda,ldb,ldp,clrp,decb,clk;
input [15:0] data_in;
output eqz;
wire[15:0] x,y,z,bout,bus;
assign bus = data_in;


pipo1 a(x,bus,lda,clk);
pipo2 p(y,z,ldp,clrp,clk);
cntr b(bout,bus,ldb,decb,clk);
add ad(z,x,y);
eqz  comp(eqz,bout);

endmodule

module pipo1(dout,din,ld,clk);
 input[15:0]din;
 input ld,clk;
 output reg[15:0]dout;
 always @(posedge clk)
 if(ld) dout<=din;
 
endmodule

module pipo2(dout,din,ld,clr,clk);
input [15:0] din;
input ld,clr,clk;
output reg[15:0]dout;
always @(posedge clk)
if(clr) dout<=16'b0;
else if(ld) dout<=din;

endmodule

module add(out,in1,in2);
input[15:0]in1,in2;
output reg[15:0] out;
always @(*)
out=in1+in2;
endmodule

module eqz(eq,data);
input[15:0] data;
output eq;
assign eq=(data==0);
endmodule

module cntr(dout,din,ld,dec,clk);
input[15:0]din;
input ld,dec,clk;
output reg[15:0] dout;
always @(posedge clk)
  if(ld) dout<=din;
  else if(dec) dout<=dout-1;

endmodule

mul_algo/mul_test.v
module mul_test;
reg[15:0] data_in;
reg clk,start;
wire done;
mul_datapath dp(eqz,lda, ldb,ldp,clrp,decb,data_in,clk);
mul_control con(lda,ldb,ldp,clrp,decb,done,clk,eqz,start);

initial begin
  clk=1'b0;
  #3 start=1'b1;
  #500 $finish;
end

always #5 clk=~clk;

initial begin
  #17 data_in=17;
  #10 data_in=5;
end

initial begin
  $monitor($time,"%d  %b",dp.y,done);
  $dumpfile("mul.vcd");
  $dumpvars(0,mul_test);
end

endmodule

mul_algo/mul.vcd
$date
	Fri May 30 21:02:14 2025
$end
$version
	Icarus Verilog
$end
$timescale
	1s
$end
$scope module mul_test $end
$var wire 1 ! ldp $end
$var wire 1 " ldb $end
$var wire 1 # lda $end
$var wire 1 $ eqz $end
$var wire 1 % done $end
$var wire 1 & decb $end
$var wire 1 ' clrp $end
$var reg 1 ( clk $end
$var reg 16 ) data_in [15:0] $end
$var reg 1 * start $end
$scope module con $end
$var wire 1 ( clk $end
$var wire 1 * start $end
$var wire 1 $ eqz $end
$var parameter 3 + s0 $end
$var parameter 3 , s1 $end
$var parameter 3 - s2 $end
$var parameter 3 . s3 $end
$var parameter 3 / s4 $end
$var reg 1 ' clrp $end
$var reg 1 & decb $end
$var reg 1 % done $end
$var reg 1 # lda $end
$var reg 1 " ldb $end
$var reg 1 ! ldp $end
$var reg 3 0 state [2:0] $end
$upscope $end
$scope module dp $end
$var wire 16 1 bus [15:0] $end
$var wire 1 ( clk $end
$var wire 1 ' clrp $end
$var wire 16 2 data_in [15:0] $end
$var wire 1 & decb $end
$var wire 1 # lda $end
$var wire 1 " ldb $end
$var wire 1 ! ldp $end
$var wire 16 3 z [15:0] $end
$var wire 16 4 y [15:0] $end
$var wire 16 5 x [15:0] $end
$var wire 1 $ eqz $end
$var wire 16 6 bout [15:0] $end
$scope module a $end
$var wire 1 ( clk $end
$var wire 16 7 din [15:0] $end
$var wire 1 # ld $end
$var reg 16 8 dout [15:0] $end
$upscope $end
$scope module ad $end
$var wire 16 9 in1 [15:0] $end
$var wire 16 : in2 [15:0] $end
$var reg 16 ; out [15:0] $end
$upscope $end
$scope module b $end
$var wire 1 ( clk $end
$var wire 1 & dec $end
$var wire 16 < din [15:0] $end
$var wire 1 " ld $end
$var reg 16 = dout [15:0] $end
$upscope $end
$scope module comp $end
$var wire 16 > data [15:0] $end
$var wire 1 $ eq $end
$upscope $end
$scope module p $end
$var wire 1 ( clk $end
$var wire 1 ' clr $end
$var wire 16 ? din [15:0] $end
$var wire 1 ! ld $end
$var reg 16 @ dout [15:0] $end
$upscope $end
$upscope $end
$upscope $end
$enddefinitions $end
$comment Show the parameter values. $end
$dumpall
b100 /
b11 .
b10 -
b1 ,
b0 +
$end
#0
$dumpvars
bx @
bx ?
bx >
bx =
bx <
bx ;
bx :
bx 9
bx 8
bx 7
bx 6
bx 5
bx 4
bx 3
bx 2
bx 1
bx 0
x*
bx )
0(
x'
x&
x%
x$
x#
x"
x!
$end
#3
1*
#5
b0 0
1(
#6
0&
0'
0!
0"
0#
#10
0(
#15
b1 0
1(
#16
1#
#17
b10001 1
b10001 7
b10001 <
b10001 )
b10001 2
#20
0(
#25
b10001 5
b10001 8
b10001 9
b10 0
1(
#26
1'
1"
0#
#27
b101 1
b101 7
b101 <
b101 )
b101 2
#30
0(
#35
b10001 3
b10001 ;
b10001 ?
b11 0
0$
b101 6
b101 =
b101 >
b0 4
b0 :
b0 @
1(
#36
1&
0'
1!
0"
#40
0(
#45
b100010 3
b100010 ;
b100010 ?
b10001 4
b10001 :
b10001 @
b100 6
b100 =
b100 >
1(
#50
0(
#55
b110011 3
b110011 ;
b110011 ?
b11 6
b11 =
b11 >
b100010 4
b100010 :
b100010 @
1(
#60
0(
#65
b1000100 3
b1000100 ;
b1000100 ?
b110011 4
b110011 :
b110011 @
b10 6
b10 =
b10 >
1(
#70
0(
#75
b1010101 3
b1010101 ;
b1010101 ?
b1 6
b1 =
b1 >
b1000100 4
b1000100 :
b1000100 @
1(
#80
0(
#85
b1100110 3
b1100110 ;
b1100110 ?
b1010101 4
b1010101 :
b1010101 @
1$
b0 6
b0 =
b0 >
1(
#87
b100 0
#88
0&
0!
1%
